pypkg_generator/__init__.py
pypkg_generator/__main__.py
pypkg_generator/config.py
pypkg_generator/exceptions.py
pypkg_generator/package_generator.py
pypkg_generator-0.5.0.dist-info/LICENSE
pypkg_generator-0.5.0.dist-info/METADATA
pypkg_generator-0.5.0.dist-info/WHEEL
pypkg_generator-0.5.0.dist-info/entry_points.txt
pypkg_generator-0.5.0.dist-info/top_level.txt
pypkg_generator-0.5.0.dist-info/RECORD
