Metadata-Version: 2.1
Name: pypkg-generator
Version: 0.5.0
Summary: Creates a new python package from basic template
Home-page: https://github.com/dany2691/pypkg-generator
Author: Daniel Omar Vergara Pérez
Author-email: daniel.omar.vergara@gmail.com
License: MIT
Platform: UNKNOWN
Classifier: License :: OSI Approved :: MIT License
Classifier: Programming Language :: Python :: 3.5
Classifier: Programming Language :: Python :: 3.6
Classifier: Programming Language :: Python :: 3.7
Classifier: Programming Language :: Python :: Implementation :: CPython
Classifier: Programming Language :: Python :: Implementation :: PyPy
Requires-Dist: click (>=7.0.0)
Requires-Dist: colored (>=1.3.93)
